fds/__init__.py
fds/sdk/__init__.py
fds/sdk/CompanyLogoAPIforDigitalPortals/__init__.py
fds/sdk/CompanyLogoAPIforDigitalPortals/api_client.py
fds/sdk/CompanyLogoAPIforDigitalPortals/configuration.py
fds/sdk/CompanyLogoAPIforDigitalPortals/exceptions.py
fds/sdk/CompanyLogoAPIforDigitalPortals/model_utils.py
fds/sdk/CompanyLogoAPIforDigitalPortals/rest.py
fds/sdk/CompanyLogoAPIforDigitalPortals/api/__init__.py
fds/sdk/CompanyLogoAPIforDigitalPortals/api/company_api.py
fds/sdk/CompanyLogoAPIforDigitalPortals/apis/__init__.py
fds/sdk/CompanyLogoAPIforDigitalPortals/model/__init__.py
fds/sdk/CompanyLogoAPIforDigitalPortals/model/attributes_member.py
fds/sdk/CompanyLogoAPIforDigitalPortals/model/cursor_based_pagination_output_object.py
fds/sdk/CompanyLogoAPIforDigitalPortals/model/cursor_based_pagination_output_object_without_total.py
fds/sdk/CompanyLogoAPIforDigitalPortals/model/error_meta_object.py
fds/sdk/CompanyLogoAPIforDigitalPortals/model/error_object.py
fds/sdk/CompanyLogoAPIforDigitalPortals/model/inline_response200.py
fds/sdk/CompanyLogoAPIforDigitalPortals/model/inline_response200_data.py
fds/sdk/CompanyLogoAPIforDigitalPortals/model/inline_response200_data_large.py
fds/sdk/CompanyLogoAPIforDigitalPortals/model/inline_response200_data_medium.py
fds/sdk/CompanyLogoAPIforDigitalPortals/model/inline_response200_data_small.py
fds/sdk/CompanyLogoAPIforDigitalPortals/model/inline_response200_data_vector.py
fds/sdk/CompanyLogoAPIforDigitalPortals/model/inline_response200_meta.py
fds/sdk/CompanyLogoAPIforDigitalPortals/model/language_member.py
fds/sdk/CompanyLogoAPIforDigitalPortals/model/offset_based_pagination_output_object.py
fds/sdk/CompanyLogoAPIforDigitalPortals/model/offset_based_pagination_output_object_without_total.py
fds/sdk/CompanyLogoAPIforDigitalPortals/model/partial_output_object.py
fds/sdk/CompanyLogoAPIforDigitalPortals/model/status_object.py
fds/sdk/CompanyLogoAPIforDigitalPortals/models/__init__.py
fds.sdk.CompanyLogoAPIforDigitalPortals-0.10.12.dist-info/LICENSE
fds.sdk.CompanyLogoAPIforDigitalPortals-0.10.12.dist-info/METADATA
fds.sdk.CompanyLogoAPIforDigitalPortals-0.10.12.dist-info/WHEEL
fds.sdk.CompanyLogoAPIforDigitalPortals-0.10.12.dist-info/top_level.txt
fds.sdk.CompanyLogoAPIforDigitalPortals-0.10.12.dist-info/RECORD
